file_stream/__init__.py
file_stream/__main__.py
file_stream/executor.py
file_stream/filter.py
file_stream/logic.py
file_stream/route.py
file_stream/source.py
file_stream/stastic.py
file_stream/utils.py
file_stream/writer.py
file_stream-0.2.4.dist-info/DESCRIPTION.rst
file_stream-0.2.4.dist-info/METADATA
file_stream-0.2.4.dist-info/RECORD
file_stream-0.2.4.dist-info/WHEEL
file_stream-0.2.4.dist-info/metadata.json
file_stream-0.2.4.dist-info/top_level.txt
