Metadata-Version: 2.0
Name: file-stream
Version: 0.2.4
Summary: process data as stream.
Home-page: https://github.com/nutalk/file_stream
Author: Nutalk
Author-email: ht2005112@hotmail.com
License: BSD
Keywords: file
Platform: UNKNOWN
Classifier: Development Status :: 3 - Alpha
Classifier: Topic :: Utilities
Classifier: License :: OSI Approved :: MIT License
Classifier: Programming Language :: Python :: 3
Classifier: Programming Language :: Python :: 3.5
Classifier: Programming Language :: Python :: 3.5
Classifier: Programming Language :: Python :: 3.6
Classifier: Programming Language :: Python :: 3.7
Classifier: Programming Language :: Python :: 3.8
Classifier: Programming Language :: Python :: Implementation :: CPython
